maskgit/__init__.py
maskgit/inference.py
maskgit/utils.py
maskgit/configs/__init__.py
maskgit/configs/base_config.py
maskgit/configs/maskgit_class_cond_config.py
maskgit/configs/vqgan_config.py
maskgit/libml/__init__.py
maskgit/libml/losses.py
maskgit/libml/mask_schedule.py
maskgit/libml/parallel_decode.py
maskgit/nets/__init__.py
maskgit/nets/discriminator.py
maskgit/nets/layers.py
maskgit/nets/maskgit_transformer.py
maskgit/nets/vqgan_tokenizer.py
maskgit-0.0.1.dev0.dist-info/LICENSE
maskgit-0.0.1.dev0.dist-info/METADATA
maskgit-0.0.1.dev0.dist-info/WHEEL
maskgit-0.0.1.dev0.dist-info/top_level.txt
maskgit-0.0.1.dev0.dist-info/RECORD
