Metadata-Version: 2.1
Name: maskgit
Version: 0.0.1.dev0
Summary: maskgit
Author: Shadow Walker
Keywords: maskgit
Classifier: Programming Language :: Python :: 3
Classifier: Programming Language :: Python :: 3.8
Classifier: Programming Language :: Python :: 3.9
Classifier: Programming Language :: Python :: 3.10
Classifier: Programming Language :: Python :: 3.11
Classifier: Programming Language :: Python :: 3.12
License-File: LICENSE
